pybrock/.gitignore
pybrock/__init__.py
pybrock/data.py
pybrock/sports.py
pybrock/utils.py
pybrock-0.14.dist-info/WHEEL
pybrock-0.14.dist-info/METADATA
pybrock-0.14.dist-info/RECORD
